<?xml version="1.0" encoding="utf-8"?>

<spacecraft>

  <model file="GameData/models/Frigate.xml" />

  <parameters>
    <defaultspeed value="50" />
    <minspeed value="30" />
    <maxspeed value="120" />
    <forwardacceleration value="25" />
    <backwardacceleration value="25" />
    <defaultspeedacceleration value="40" />

    <maxlateraldeflection value="3" />
    <maxattitudedeflection value="4" />
    <attitudereduction value="50" />

    <followerattitude x="0" y="0" z="-0.4" />
    <followerposition x="0" y="-10" z="6" />
    <followerconvergence value="100" />
  </parameters>

</spacecraft>